agenteval/__init__.py
agenteval/cli.py
agenteval/cli_utils.py
agenteval/config.py
agenteval/io.py
agenteval/local_cost.py
agenteval/log.py
agenteval/models.py
agenteval/score.py
agenteval/summary.py
agenteval/leaderboard/__init__.py
agenteval/leaderboard/dataset_features.yml
agenteval/leaderboard/model_name_mapping.py
agenteval/leaderboard/models.py
agenteval/leaderboard/schema_generator.py
agenteval/leaderboard/upload.py
agenteval/leaderboard/view.py
agent_eval-0.1.44.dist-info/METADATA
agent_eval-0.1.44.dist-info/WHEEL
agent_eval-0.1.44.dist-info/entry_points.txt
agent_eval-0.1.44.dist-info/top_level.txt
agent_eval-0.1.44.dist-info/RECORD
