Metadata-Version: 2.4
Name: agent-eval
Version: 0.1.44
Summary: Agent evaluation toolkit
Project-URL: Homepage, https://github.com/allenai/agent-eval
Requires-Python: >=3.10
Requires-Dist: click
Requires-Dist: inspect-ai<0.3.137,>=0.3.104
Requires-Dist: litellm<=1.75.8,>=1.67.4.post1
Requires-Dist: pydantic>=2.0.0
Requires-Dist: huggingface_hub
Requires-Dist: pyarrow
Requires-Dist: datasets
Provides-Extra: dev
Requires-Dist: black==24.2.0; extra == "dev"
Requires-Dist: isort; extra == "dev"
Requires-Dist: autoflake; extra == "dev"
Requires-Dist: flake8; extra == "dev"
Requires-Dist: flake8-pyproject; extra == "dev"
Requires-Dist: flake8-pep585; extra == "dev"
Requires-Dist: flake8-new-union-types; extra == "dev"
Requires-Dist: pytest; extra == "dev"
Requires-Dist: pytest-asyncio; extra == "dev"
Requires-Dist: mypy==1.15; extra == "dev"
Requires-Dist: types-PyYAML; extra == "dev"
Requires-Dist: types-setuptools; extra == "dev"
Requires-Dist: pandas-stubs; extra == "dev"
Requires-Dist: types-seaborn; extra == "dev"
Provides-Extra: leaderboard
Requires-Dist: seaborn; extra == "leaderboard"
Requires-Dist: matplotlib; extra == "leaderboard"
Requires-Dist: pandas; extra == "leaderboard"
